phaser/__init__.py
phaser/__main__.py
phaser/execute.py
phaser/main.py
phaser/observer.py
phaser/plan.py
phaser/py.typed
phaser/state.py
phaser/types.py
phaser/engines/common/__init__.py
phaser/engines/common/noise_models.py
phaser/engines/common/output.py
phaser/engines/common/position_correction.py
phaser/engines/common/regularizers.py
phaser/engines/common/simulation.py
phaser/engines/conventional/__init__.py
phaser/engines/conventional/run.py
phaser/engines/conventional/solvers.py
phaser/engines/gradient/run.py
phaser/engines/gradient/solvers.py
phaser/hooks/__init__.py
phaser/hooks/hook.py
phaser/hooks/object.py
phaser/hooks/preprocessing.py
phaser/hooks/probe.py
phaser/hooks/regularization.py
phaser/hooks/scan.py
phaser/hooks/schedule.py
phaser/hooks/solver.py
phaser/hooks/tilt.py
phaser/hooks/io/empad.py
phaser/hooks/io/manual.py
phaser/io/__init__.py
phaser/io/empad.py
phaser/utils/__init__.py
phaser/utils/_cuda_kernels.py
phaser/utils/_jax_kernels.py
phaser/utils/analysis.py
phaser/utils/image.py
phaser/utils/io.py
phaser/utils/misc.py
phaser/utils/num.py
phaser/utils/object.py
phaser/utils/optics.py
phaser/utils/physics.py
phaser/utils/plotting.py
phaser/utils/scan.py
phaser/web/__init__.py
phaser/web/notebook.py
phaser/web/routes.py
phaser/web/server.py
phaser/web/slurm.py
phaser/web/types.py
phaser/web/util.py
phaser/web/worker.py
phaser/web/dist/9573273f862f4f5d9644.module.wasm
phaser/web/dist/bundle-dashboard.js
phaser/web/dist/bundle-manager.js
phaser/web/dist/bundle-vendors-node_modules_wasm-array_wasm_array_js.js
phaser/web/templates/base.html
phaser/web/templates/dashboard.html
phaser/web/templates/manager.html
phaserem-0.2.dist-info/licenses/LICENSE.txt
phaserem-0.2.dist-info/METADATA
phaserem-0.2.dist-info/WHEEL
phaserem-0.2.dist-info/entry_points.txt
phaserem-0.2.dist-info/top_level.txt
phaserem-0.2.dist-info/RECORD
