Metadata-Version: 2.4
Name: phaserEM
Version: 0.2
Summary: Weapon of choice for electron ptychographic reconstructions
Author-email: Colin Gilgenbach <hexane@mit.edu>
License-Expression: MPL-2.0
Project-URL: Repository, https://github.com/hexane360/phaser.git
Project-URL: Documentation, https://hexane360.github.io/phaser/dev
Keywords: science,atoms,materials,chemistry
Classifier: Development Status :: 4 - Beta
Classifier: Programming Language :: Python :: 3
Classifier: Programming Language :: Python :: 3 :: Only
Classifier: Programming Language :: Python :: 3.10
Classifier: Programming Language :: Python :: 3.11
Classifier: Programming Language :: Python :: 3.12
Classifier: Programming Language :: Python :: 3.13
Classifier: Intended Audience :: Science/Research
Classifier: Topic :: Scientific/Engineering :: Physics
Classifier: Typing :: Typed
Requires-Python: >=3.10
License-File: LICENSE.txt
Requires-Dist: numpy<2.6,>=1.22
Requires-Dist: scipy<1.19,>=1.7.0
Requires-Dist: matplotlib~=3.8
Requires-Dist: h5py~=3.8
Requires-Dist: pyyaml>=5.3.1
Requires-Dist: click~=8.1.0
Requires-Dist: rich<15,>=12.0.0
Requires-Dist: tifffile>=2023.8.25
Requires-Dist: py-pane==0.11.3
Requires-Dist: typing_extensions~=4.7
Provides-Extra: dev
Requires-Dist: pytest>=6.2.4; extra == "dev"
Requires-Dist: pytest-cov>=3.0.0; extra == "dev"
Requires-Dist: coveragepy-lcov>=0.1.1; extra == "dev"
Provides-Extra: cupy11
Requires-Dist: cupy-cuda11x>=12.0.0; extra == "cupy11"
Requires-Dist: pynvml>=11.0.0; extra == "cupy11"
Provides-Extra: cupy12
Requires-Dist: cupy-cuda12x>=12.0.0; extra == "cupy12"
Requires-Dist: pynvml>=11.0.0; extra == "cupy12"
Provides-Extra: jax
Requires-Dist: jax<0.8,>=0.4.25; extra == "jax"
Requires-Dist: optax>=0.2.2; extra == "jax"
Provides-Extra: web
Requires-Dist: Quart>=0.20.0; extra == "web"
Requires-Dist: backoff==2.2.1; extra == "web"
Requires-Dist: requests>=2.31.0; extra == "web"
Provides-Extra: docs
Requires-Dist: mkdocs==1.6.1; extra == "docs"
Requires-Dist: mkdocs-material==9.6.11; extra == "docs"
Requires-Dist: mkdocstrings[python]==0.29.1; extra == "docs"
Requires-Dist: markdown-include==0.8.1; extra == "docs"
Requires-Dist: mike==2.1.3; extra == "docs"
Requires-Dist: black>=25.1.0; extra == "docs"
Dynamic: license-file
